PyGeoTimes/__init__.py
PyGeoTimes-1.4.dist-info/METADATA
PyGeoTimes-1.4.dist-info/WHEEL
PyGeoTimes-1.4.dist-info/top_level.txt
PyGeoTimes-1.4.dist-info/RECORD
