Metadata-Version: 2.1
Name: PyGeoTimes
Version: 1.4
Summary: PyGeoTimes extract geological Times from English texts
Home-page: UNKNOWN
Author: Abhay He
Author-email: 1452245133@qq.com
License: UNKNOWN
Platform: UNKNOWN
Classifier: Programming Language :: Python :: 3
Classifier: License :: OSI Approved :: MIT License
Classifier: Operating System :: OS Independent
Requires-Python: >=3
Requires-Dist: pillow
